ochsner_web2com/__init__.py
ochsner_web2com/web2com.py
ochsner_web2com-0.1.7.dist-info/METADATA
ochsner_web2com-0.1.7.dist-info/WHEEL
ochsner_web2com-0.1.7.dist-info/licenses/LICENSE
ochsner_web2com-0.1.7.dist-info/RECORD
