Metadata-Version: 2.3
Name: ochsner_web2com
Version: 0.1.7
Summary: Access to the ochsner web2com interface
Project-URL: Homepage, https://github.com/ahackl/pypi_ochsner_web2com
Project-URL: Bug Tracker, https://github.com/ahackl/pypi_ochsner_web2com/issues
Author-email: Alexander Hackl <pypi@eccoz.de>
Classifier: License :: OSI Approved :: MIT License
Classifier: Operating System :: OS Independent
Classifier: Programming Language :: Python :: 3
Requires-Python: >=3.7
Requires-Dist: requests
Requires-Dist: xmltodict
